mindmatrix/__abort__.py
mindmatrix/__init__.py
mindmatrix/_mindmatrix.py
mindmatrix/agent_base/__init__.py
mindmatrix/agent_base/_base.py
mindmatrix/agent_base/_models.py
mindmatrix/builtins_/.gitkeep
mindmatrix/builtins_/tasks/__init__.py
mindmatrix/builtins_/tasks/embeddings.py
mindmatrix/datasets_/sharegpt.py
mindmatrix/knowledge_base/__init__.py
mindmatrix/knowledge_base/_base.py
mindmatrix/memory_base/__init__.py
mindmatrix/memory_base/_mem0.py
mindmatrix/memory_base/_memory.py
mindmatrix/memory_base/_memory_manager.py
mindmatrix/py.typed
mindmatrix/utils/http_client.py
mindmatrix/utils/mindmatrix_client.py
mindmatrix/utils/mixins.py
mindmatrix/utils/reranker_client.py
mindmatrix/web/__init__.py
mindmatrix/web/_app.py
mindmatrix/web/_contextvars.py
mindmatrix/web/_endpoints.py
mindmatrix/web/_openai_adapter.py
mindmatrix/web/_security.py
mindmatrix/web/_sse_adapter.py
mindmatrix-0.1.0.post3.dist-info/WHEEL
mindmatrix-0.1.0.post3.dist-info/METADATA
mindmatrix-0.1.0.post3.dist-info/RECORD
