Metadata-Version: 2.3
Name: mindmatrix
Version: 0.1.0.post3
Summary: MindMatrix 是一个基于 Agno 的轻量级智能体"应用"框架，专为快速构建具有RAG、记忆和可访问能力的生产级多智能体系统而设计。
Requires-Dist: agno>=1.7.7,<1.8.0
Requires-Dist: fastapi>=0.116.1
Requires-Dist: httpx[socks]>=0.28.1
Requires-Dist: loguru>=0.7.3
Requires-Dist: openai>=1.98.0
Requires-Dist: prefect>=3.4.14
Requires-Dist: pymilvus>=2.6.0
Requires-Dist: sse-starlette>=3.0.2
Requires-Python: >=3.12, <3.14
